<?xml version="1.0" encoding="utf-8"?>
<AnimationFile>
  <Animations AnimationCount="3" />
  <Object ObjectName="C:\Users\fullsail\Desktop\nightingale fonts\BrockFont.png">
    <Animation FrameCount="26" AnimName="Lower">
      <Frame Event="a" DrawLeft="0" DrawTop="23" DrawRight="14" DrawBottom="40" CollisionLeft="-1" CollisionTop="-1" CollisionRight="0" CollisionBottom="0" EventLeft="-1" EventTop="-1" EventRight="0" EventBottom="0" AnchorLeft="8" AnchorTop="23" Duration="0.25" />
      <Frame Event="b" DrawLeft="15" DrawTop="16" DrawRight="29" DrawBottom="38" CollisionLeft="-1" CollisionTop="-1" CollisionRight="0" CollisionBottom="0" EventLeft="-1" EventTop="-1" EventRight="0" EventBottom="0" AnchorLeft="24" AnchorTop="23" Duration="0.5" />
      <Frame Event="c" DrawLeft="32" DrawTop="24" DrawRight="44" DrawBottom="39" CollisionLeft="-1" CollisionTop="-1" CollisionRight="0" CollisionBottom="0" EventLeft="-1" EventTop="-1" EventRight="0" EventBottom="0" AnchorLeft="38" AnchorTop="23" Duration="0.5" />
      <Frame Event="d" DrawLeft="46" DrawTop="16" DrawRight="59" DrawBottom="38" CollisionLeft="-1" CollisionTop="-1" CollisionRight="0" CollisionBottom="0" EventLeft="-1" EventTop="-1" EventRight="0" EventBottom="0" AnchorLeft="51" AnchorTop="23" Duration="0.5" />
      <Frame Event="e" DrawLeft="60" DrawTop="22" DrawRight="74" DrawBottom="41" CollisionLeft="-1" CollisionTop="-1" CollisionRight="0" CollisionBottom="0" EventLeft="-1" EventTop="-1" EventRight="0" EventBottom="0" AnchorLeft="67" AnchorTop="23" Duration="0.5" />
      <Frame Event="f" DrawLeft="74" DrawTop="17" DrawRight="83" DrawBottom="35" CollisionLeft="-1" CollisionTop="-1" CollisionRight="0" CollisionBottom="0" EventLeft="-1" EventTop="-1" EventRight="0" EventBottom="0" AnchorLeft="79" AnchorTop="23" Duration="0.5" />
      <Frame Event="g" DrawLeft="83" DrawTop="23" DrawRight="98" DrawBottom="50" CollisionLeft="-1" CollisionTop="-1" CollisionRight="0" CollisionBottom="0" EventLeft="-1" EventTop="-1" EventRight="0" EventBottom="0" AnchorLeft="89" AnchorTop="23" Duration="0.5" />
      <Frame Event="h" DrawLeft="97" DrawTop="18" DrawRight="112" DrawBottom="41" CollisionLeft="-1" CollisionTop="-1" CollisionRight="0" CollisionBottom="0" EventLeft="-1" EventTop="-1" EventRight="0" EventBottom="0" AnchorLeft="106" AnchorTop="23" Duration="0.5" />
      <Frame Event="i" DrawLeft="114" DrawTop="20" DrawRight="119" DrawBottom="38" CollisionLeft="-1" CollisionTop="-1" CollisionRight="0" CollisionBottom="0" EventLeft="-1" EventTop="-1" EventRight="0" EventBottom="0" AnchorLeft="116" AnchorTop="23" Duration="0.5" />
      <Frame Event="j" DrawLeft="119" DrawTop="17" DrawRight="129" DrawBottom="45" CollisionLeft="-1" CollisionTop="-1" CollisionRight="0" CollisionBottom="0" EventLeft="-1" EventTop="-1" EventRight="0" EventBottom="0" AnchorLeft="125" AnchorTop="23" Duration="0.5" />
      <Frame Event="k" DrawLeft="128" DrawTop="14" DrawRight="142" DrawBottom="40" CollisionLeft="-1" CollisionTop="-1" CollisionRight="0" CollisionBottom="0" EventLeft="-1" EventTop="-1" EventRight="0" EventBottom="0" AnchorLeft="135" AnchorTop="23" Duration="0.5" />
      <Frame Event="l" DrawLeft="143" DrawTop="15" DrawRight="150" DrawBottom="39" CollisionLeft="-1" CollisionTop="-1" CollisionRight="0" CollisionBottom="0" EventLeft="-1" EventTop="-1" EventRight="0" EventBottom="0" AnchorLeft="145" AnchorTop="23" Duration="0.5" />
      <Frame Event="m" DrawLeft="149" DrawTop="22" DrawRight="173" DrawBottom="37" CollisionLeft="-1" CollisionTop="-1" CollisionRight="0" CollisionBottom="0" EventLeft="-1" EventTop="-1" EventRight="0" EventBottom="0" AnchorLeft="162" AnchorTop="23" Duration="0.5" />
      <Frame Event="n" DrawLeft="172" DrawTop="23" DrawRight="189" DrawBottom="38" CollisionLeft="-1" CollisionTop="-1" CollisionRight="0" CollisionBottom="0" EventLeft="-1" EventTop="-1" EventRight="0" EventBottom="0" AnchorLeft="183" AnchorTop="23" Duration="0.5" />
      <Frame Event="o" DrawLeft="188" DrawTop="24" DrawRight="202" DrawBottom="38" CollisionLeft="-1" CollisionTop="-1" CollisionRight="0" CollisionBottom="0" EventLeft="-1" EventTop="-1" EventRight="0" EventBottom="0" AnchorLeft="194" AnchorTop="23" Duration="0.5" />
      <Frame Event="p" DrawLeft="203" DrawTop="25" DrawRight="218" DrawBottom="46" CollisionLeft="-1" CollisionTop="-1" CollisionRight="0" CollisionBottom="0" EventLeft="-1" EventTop="-1" EventRight="0" EventBottom="0" AnchorLeft="209" AnchorTop="23" Duration="0.5" />
      <Frame Event="q" DrawLeft="217" DrawTop="23" DrawRight="235" DrawBottom="46" CollisionLeft="-1" CollisionTop="-1" CollisionRight="0" CollisionBottom="0" EventLeft="-1" EventTop="-1" EventRight="0" EventBottom="0" AnchorLeft="225" AnchorTop="23" Duration="0.5" />
      <Frame Event="r" DrawLeft="233" DrawTop="24" DrawRight="246" DrawBottom="48" CollisionLeft="-1" CollisionTop="-1" CollisionRight="0" CollisionBottom="0" EventLeft="-1" EventTop="-1" EventRight="0" EventBottom="0" AnchorLeft="239" AnchorTop="23" Duration="0.5" />
      <Frame Event="s" DrawLeft="247" DrawTop="23" DrawRight="262" DrawBottom="42" CollisionLeft="-1" CollisionTop="-1" CollisionRight="0" CollisionBottom="0" EventLeft="-1" EventTop="-1" EventRight="0" EventBottom="0" AnchorLeft="251" AnchorTop="23" Duration="0.5" />
      <Frame Event="t" DrawLeft="261" DrawTop="18" DrawRight="274" DrawBottom="41" CollisionLeft="-1" CollisionTop="-1" CollisionRight="0" CollisionBottom="0" EventLeft="-1" EventTop="-1" EventRight="0" EventBottom="0" AnchorLeft="268" AnchorTop="23" Duration="0.5" />
      <Frame Event="u" DrawLeft="273" DrawTop="23" DrawRight="287" DrawBottom="38" CollisionLeft="-1" CollisionTop="-1" CollisionRight="0" CollisionBottom="0" EventLeft="-1" EventTop="-1" EventRight="0" EventBottom="0" AnchorLeft="281" AnchorTop="23" Duration="0.5" />
      <Frame Event="v" DrawLeft="288" DrawTop="22" DrawRight="304" DrawBottom="38" CollisionLeft="-1" CollisionTop="-1" CollisionRight="0" CollisionBottom="0" EventLeft="-1" EventTop="-1" EventRight="0" EventBottom="0" AnchorLeft="295" AnchorTop="23" Duration="0.5" />
      <Frame Event="w" DrawLeft="304" DrawTop="23" DrawRight="323" DrawBottom="39" CollisionLeft="-1" CollisionTop="-1" CollisionRight="0" CollisionBottom="0" EventLeft="-1" EventTop="-1" EventRight="0" EventBottom="0" AnchorLeft="312" AnchorTop="23" Duration="0.5" />
      <Frame Event="x" DrawLeft="324" DrawTop="24" DrawRight="338" DrawBottom="41" CollisionLeft="-1" CollisionTop="-1" CollisionRight="0" CollisionBottom="0" EventLeft="-1" EventTop="-1" EventRight="0" EventBottom="0" AnchorLeft="329" AnchorTop="23" Duration="0.5" />
      <Frame Event="y" DrawLeft="338" DrawTop="24" DrawRight="355" DrawBottom="45" CollisionLeft="-1" CollisionTop="-1" CollisionRight="0" CollisionBottom="0" EventLeft="-1" EventTop="-1" EventRight="0" EventBottom="0" AnchorLeft="347" AnchorTop="23" Duration="0.5" />
      <Frame Event="z" DrawLeft="355" DrawTop="24" DrawRight="369" DrawBottom="40" CollisionLeft="-1" CollisionTop="-1" CollisionRight="0" CollisionBottom="0" EventLeft="-1" EventTop="-1" EventRight="0" EventBottom="0" AnchorLeft="360" AnchorTop="23" Duration="0.5" />
    </Animation>
    <Animation FrameCount="26" AnimName="Upper">
      <Frame Event="A" DrawLeft="376" DrawTop="18" DrawRight="396" DrawBottom="39" CollisionLeft="-1" CollisionTop="-1" CollisionRight="0" CollisionBottom="0" EventLeft="-1" EventTop="-1" EventRight="0" EventBottom="0" AnchorLeft="387" AnchorTop="18" Duration="0.25" />
      <Frame Event="B" DrawLeft="396" DrawTop="19" DrawRight="416" DrawBottom="43" CollisionLeft="-1" CollisionTop="-1" CollisionRight="0" CollisionBottom="0" EventLeft="-1" EventTop="-1" EventRight="0" EventBottom="0" AnchorLeft="405" AnchorTop="18" Duration="0.5" />
      <Frame Event="C" DrawLeft="418" DrawTop="20" DrawRight="438" DrawBottom="43" CollisionLeft="-1" CollisionTop="-1" CollisionRight="0" CollisionBottom="0" EventLeft="-1" EventTop="-1" EventRight="0" EventBottom="0" AnchorLeft="428" AnchorTop="18" Duration="0.5" />
      <Frame Event="D" DrawLeft="439" DrawTop="20" DrawRight="457" DrawBottom="39" CollisionLeft="-1" CollisionTop="-1" CollisionRight="0" CollisionBottom="0" EventLeft="-1" EventTop="-1" EventRight="0" EventBottom="0" AnchorLeft="450" AnchorTop="17" Duration="0.5" />
      <Frame Event="E" DrawLeft="461" DrawTop="18" DrawRight="476" DrawBottom="42" CollisionLeft="-1" CollisionTop="-1" CollisionRight="0" CollisionBottom="0" EventLeft="-1" EventTop="-1" EventRight="0" EventBottom="0" AnchorLeft="469" AnchorTop="17" Duration="0.5" />
      <Frame Event="F" DrawLeft="478" DrawTop="18" DrawRight="494" DrawBottom="39" CollisionLeft="-1" CollisionTop="-1" CollisionRight="0" CollisionBottom="0" EventLeft="-1" EventTop="-1" EventRight="0" EventBottom="0" AnchorLeft="488" AnchorTop="17" Duration="0.5" />
      <Frame Event="G" DrawLeft="497" DrawTop="18" DrawRight="513" DrawBottom="39" CollisionLeft="-1" CollisionTop="-1" CollisionRight="0" CollisionBottom="0" EventLeft="-1" EventTop="-1" EventRight="0" EventBottom="0" AnchorLeft="506" AnchorTop="17" Duration="0.5" />
      <Frame Event="H" DrawLeft="518" DrawTop="19" DrawRight="535" DrawBottom="39" CollisionLeft="-1" CollisionTop="-1" CollisionRight="0" CollisionBottom="0" EventLeft="-1" EventTop="-1" EventRight="0" EventBottom="0" AnchorLeft="526" AnchorTop="16" Duration="0.5" />
      <Frame Event="I" DrawLeft="536" DrawTop="17" DrawRight="540" DrawBottom="40" CollisionLeft="-1" CollisionTop="-1" CollisionRight="0" CollisionBottom="0" EventLeft="-1" EventTop="-1" EventRight="0" EventBottom="0" AnchorLeft="538" AnchorTop="18" Duration="0.5" />
      <Frame Event="J" DrawLeft="543" DrawTop="17" DrawRight="556" DrawBottom="40" CollisionLeft="-1" CollisionTop="-1" CollisionRight="0" CollisionBottom="0" EventLeft="-1" EventTop="-1" EventRight="0" EventBottom="0" AnchorLeft="549" AnchorTop="19" Duration="0.5" />
      <Frame Event="K" DrawLeft="558" DrawTop="19" DrawRight="578" DrawBottom="38" CollisionLeft="-1" CollisionTop="-1" CollisionRight="0" CollisionBottom="0" EventLeft="-1" EventTop="-1" EventRight="0" EventBottom="0" AnchorLeft="569" AnchorTop="21" Duration="0.5" />
      <Frame Event="L" DrawLeft="581" DrawTop="17" DrawRight="594" DrawBottom="38" CollisionLeft="-1" CollisionTop="-1" CollisionRight="0" CollisionBottom="0" EventLeft="-1" EventTop="-1" EventRight="0" EventBottom="0" AnchorLeft="587" AnchorTop="21" Duration="0.5" />
      <Frame Event="M" DrawLeft="597" DrawTop="17" DrawRight="623" DrawBottom="40" CollisionLeft="-1" CollisionTop="-1" CollisionRight="0" CollisionBottom="0" EventLeft="-1" EventTop="-1" EventRight="0" EventBottom="0" AnchorLeft="609" AnchorTop="20" Duration="0.5" />
      <Frame Event="N" DrawLeft="623" DrawTop="18" DrawRight="642" DrawBottom="39" CollisionLeft="-1" CollisionTop="-1" CollisionRight="0" CollisionBottom="0" EventLeft="-1" EventTop="-1" EventRight="0" EventBottom="0" AnchorLeft="632" AnchorTop="20" Duration="0.5" />
      <Frame Event="O" DrawLeft="644" DrawTop="18" DrawRight="665" DrawBottom="39" CollisionLeft="-1" CollisionTop="-1" CollisionRight="0" CollisionBottom="0" EventLeft="-1" EventTop="-1" EventRight="0" EventBottom="0" AnchorLeft="653" AnchorTop="20" Duration="0.5" />
      <Frame Event="P" DrawLeft="665" DrawTop="18" DrawRight="685" DrawBottom="42" CollisionLeft="-1" CollisionTop="-1" CollisionRight="0" CollisionBottom="0" EventLeft="-1" EventTop="-1" EventRight="0" EventBottom="0" AnchorLeft="674" AnchorTop="18" Duration="0.5" />
      <Frame Event="Q" DrawLeft="686" DrawTop="17" DrawRight="705" DrawBottom="41" CollisionLeft="-1" CollisionTop="-1" CollisionRight="0" CollisionBottom="0" EventLeft="-1" EventTop="-1" EventRight="0" EventBottom="0" AnchorLeft="696" AnchorTop="20" Duration="0.5" />
      <Frame Event="R" DrawLeft="706" DrawTop="17" DrawRight="728" DrawBottom="39" CollisionLeft="-1" CollisionTop="-1" CollisionRight="0" CollisionBottom="0" EventLeft="-1" EventTop="-1" EventRight="0" EventBottom="0" AnchorLeft="716" AnchorTop="18" Duration="0.5" />
      <Frame Event="S" DrawLeft="728" DrawTop="16" DrawRight="747" DrawBottom="41" CollisionLeft="-1" CollisionTop="-1" CollisionRight="0" CollisionBottom="0" EventLeft="-1" EventTop="-1" EventRight="0" EventBottom="0" AnchorLeft="737" AnchorTop="17" Duration="0.5" />
      <Frame Event="T" DrawLeft="747" DrawTop="17" DrawRight="769" DrawBottom="46" CollisionLeft="-1" CollisionTop="-1" CollisionRight="0" CollisionBottom="0" EventLeft="-1" EventTop="-1" EventRight="0" EventBottom="0" AnchorLeft="756" AnchorTop="18" Duration="0.5" />
      <Frame Event="U" DrawLeft="768" DrawTop="17" DrawRight="787" DrawBottom="40" CollisionLeft="-1" CollisionTop="-1" CollisionRight="0" CollisionBottom="0" EventLeft="-1" EventTop="-1" EventRight="0" EventBottom="0" AnchorLeft="776" AnchorTop="18" Duration="0.5" />
      <Frame Event="V" DrawLeft="789" DrawTop="17" DrawRight="806" DrawBottom="40" CollisionLeft="-1" CollisionTop="-1" CollisionRight="0" CollisionBottom="0" EventLeft="-1" EventTop="-1" EventRight="0" EventBottom="0" AnchorLeft="797" AnchorTop="20" Duration="0.5" />
      <Frame Event="W" DrawLeft="806" DrawTop="16" DrawRight="834" DrawBottom="41" CollisionLeft="-1" CollisionTop="-1" CollisionRight="0" CollisionBottom="0" EventLeft="-1" EventTop="-1" EventRight="0" EventBottom="0" AnchorLeft="820" AnchorTop="17" Duration="0.5" />
      <Frame Event="X" DrawLeft="834" DrawTop="18" DrawRight="856" DrawBottom="41" CollisionLeft="-1" CollisionTop="-1" CollisionRight="0" CollisionBottom="0" EventLeft="-1" EventTop="-1" EventRight="0" EventBottom="0" AnchorLeft="844" AnchorTop="19" Duration="0.5" />
      <Frame Event="Y" DrawLeft="856" DrawTop="17" DrawRight="874" DrawBottom="41" CollisionLeft="-1" CollisionTop="-1" CollisionRight="0" CollisionBottom="0" EventLeft="-1" EventTop="-1" EventRight="0" EventBottom="0" AnchorLeft="865" AnchorTop="17" Duration="0.5" />
      <Frame Event="Z" DrawLeft="874" DrawTop="16" DrawRight="895" DrawBottom="38" CollisionLeft="-1" CollisionTop="-1" CollisionRight="0" CollisionBottom="0" EventLeft="-1" EventTop="-1" EventRight="0" EventBottom="0" AnchorLeft="884" AnchorTop="19" Duration="0.5" />
    </Animation>
    <Animation FrameCount="8" AnimName="Symbols">
      <Frame Event="." DrawLeft="203" DrawTop="63" DrawRight="211" DrawBottom="75" CollisionLeft="-1" CollisionTop="-1" CollisionRight="0" CollisionBottom="0" EventLeft="-1" EventTop="-1" EventRight="0" EventBottom="0" AnchorLeft="208" AnchorTop="53" Duration="0.25" />
      <Frame Event=":" DrawLeft="204" DrawTop="54" DrawRight="210" DrawBottom="75" CollisionLeft="-1" CollisionTop="-1" CollisionRight="0" CollisionBottom="0" EventLeft="-1" EventTop="-1" EventRight="0" EventBottom="0" AnchorLeft="207" AnchorTop="54" Duration="0.5" />
      <Frame Event="," DrawLeft="212" DrawTop="55" DrawRight="219" DrawBottom="80" CollisionLeft="-1" CollisionTop="-1" CollisionRight="0" CollisionBottom="0" EventLeft="-1" EventTop="-1" EventRight="0" EventBottom="0" AnchorLeft="213" AnchorTop="57" Duration="0.5" />
      <Frame Event=";" DrawLeft="219" DrawTop="56" DrawRight="226" DrawBottom="81" CollisionLeft="-1" CollisionTop="-1" CollisionRight="0" CollisionBottom="0" EventLeft="-1" EventTop="-1" EventRight="0" EventBottom="0" AnchorLeft="222" AnchorTop="60" Duration="0.5" />
      <Frame Event="'" DrawLeft="230" DrawTop="52" DrawRight="242" DrawBottom="78" CollisionLeft="-1" CollisionTop="-1" CollisionRight="0" CollisionBottom="0" EventLeft="-1" EventTop="-1" EventRight="0" EventBottom="0" AnchorLeft="236" AnchorTop="54" Duration="0.5" />
      <Frame Event="&quot;" DrawLeft="248" DrawTop="49" DrawRight="259" DrawBottom="78" CollisionLeft="-1" CollisionTop="-1" CollisionRight="0" CollisionBottom="0" EventLeft="-1" EventTop="-1" EventRight="0" EventBottom="0" AnchorLeft="253" AnchorTop="54" Duration="0.5" />
      <Frame Event="!" DrawLeft="276" DrawTop="49" DrawRight="285" DrawBottom="74" CollisionLeft="-1" CollisionTop="-1" CollisionRight="0" CollisionBottom="0" EventLeft="-1" EventTop="-1" EventRight="0" EventBottom="0" AnchorLeft="280" AnchorTop="51" Duration="0.5" />
      <Frame Event="?" DrawLeft="287" DrawTop="51" DrawRight="302" DrawBottom="74" CollisionLeft="-1" CollisionTop="-1" CollisionRight="0" CollisionBottom="0" EventLeft="-1" EventTop="-1" EventRight="0" EventBottom="0" AnchorLeft="293" AnchorTop="53" Duration="0.5" />
    </Animation>
  </Object>
</AnimationFile>